Metadata-Version: 2.1
Name: ezek-distributions
Version: 1.0
Summary: Gaussian and Binomial distributions
Author: Ezekiel Ekanem
Author-email: ezekiel.een111@gmail.com
